{ "height":2,
 "infinite":false,
 "layers":[
        {
         "data":[4, 2684354577, 15, 1610612740],
         "height":2,
         "id":1,
         "name":"Tile Layer 1",
         "opacity":1,
         "type":"tilelayer",
         "visible":true,
         "width":2,
         "x":0,
         "y":0
        }, 
        {
         "data":[3221225476, 1610612753, 3221225487, 2684354564],
         "height":2,
         "id":2,
         "name":"z",
         "opacity":1,
         "type":"tilelayer",
         "visible":true,
         "width":2,
         "x":0,
         "y":0
        }],
 "nextlayerid":3,
 "nextobjectid":1,
 "orientation":"orthogonal",
 "renderorder":"right-down",
 "tiledversion":"1.2.4",
 "tileheight":64,
 "tilesets":[
        {
         "firstgid":1,
         "source":"..\/development_tileset.json"
        }],
 "tilewidth":64,
 "type":"map",
 "version":1.2,
 "width":2
}